flyyer/__init__.py
flyyer/flyyer.py
flyyer-2.1.2.dist-info/WHEEL
flyyer-2.1.2.dist-info/METADATA
flyyer-2.1.2.dist-info/RECORD
