Metadata-Version: 2.1
Name: flyyer
Version: 2.1.2
Summary: FLYYER.io helper classes and methods
Home-page: https://flyyer.io/
License: MIT
Author: Patricio López Juri
Author-email: patricio@flyyer.io
Requires-Python: >=3.6,<4.0
Classifier: License :: OSI Approved :: MIT License
Classifier: Programming Language :: Python :: 3
Classifier: Programming Language :: Python :: 3.6
Classifier: Programming Language :: Python :: 3.7
Classifier: Programming Language :: Python :: 3.8
Classifier: Programming Language :: Python :: 3.9
Requires-Dist: PyJWT (>=2.0.1,<3.0.0)
Requires-Dist: typing-extensions (>=3.7.4,<4.0.0)
Project-URL: Repository, https://github.com/useflyyer/flyyer-python
